Workbook

Sheet Summary
A1: Decision Summary — STR vs Long-Term Rental
A2: 54 Ashburner St, Higgins ACT 2615
A4: Property value | B4: =Inputs!B5
A6: Base STR gross revenue (AirROI median) | B6: =Scenarios!D7
A7: Base STR NOI | B7: =Scenarios!D12
A8: Long-term rental NOI | B8: =Scenarios!B22
A9: Base STR advantage vs LTR (pre-amort) | B9: =Scenarios!D25
A11: Conservative STR NOI (p25) | B11: =Scenarios!C12
A12: Aggressive STR NOI (p75) | B12: =Scenarios!E12
A14: STR base net yield | B14: =Scenarios!D12/Inputs!B5
A15: LTR net yield | B15: =Scenarios!B22/Inputs!B5
A16: Break-even occupancy to match LTR (base ADR) | B16: =Scenarios!B26/(Inputs!C10*365)
A18: Verdict
A19: At median execution, STR is roughly line-ball with a $750/wk long-term rent, for much more work and risk. STR wins clearly only if run top-quartile (p75). Both yields are low because it is a $1M house — a capital-growth, low-yield market.
A25: Source: AirROI API (pulled 2026-08-08). Edit blue cells in Inputs; all else recalculates.

Sheet Inputs
A1: Canberra STR Decision Model — Inputs
A2: 54 Ashburner St, Higgins ACT 2615 · AUD · blue = editable, yellow = key assumption
A4: Property
A5: Market value | B5: 1000000 | C5: USER-PROVIDED
A6: Bedrooms / Bathrooms / Guests | B6: 4 / 2 / 8
A7: STR scenarios — AirROI percentiles for THIS property
B8: Conservative | C8: Base | D8: Aggressive
A9: Occupancy | B9: 0.36 | C9: 0.52 | D9: 0.67
A10: ADR (avg nightly rate) | B10: 251 | C10: 346 | D10: 456
A11: Gross annual revenue (AirROI) | B11: 38005 | C11: 62033 | D11: 86899
A12: ACT short-term rental levy
A13: Levy rate — current | B13: 0.05 | C13: 5% (ACT Gov)
A14: Levy rate — from 1 Jul 2027 | B14: 0.075 | C14: 7.5% legislated
A15: STR operating costs
A16: Management fee (% of revenue) | B16: 0.18 | C16: 0 if self-managed
A17: Platform fee (% of revenue) | B17: 0.03
A18: Utilities + internet (annual) | B18: 6000
A19: Insurance (annual) | B19: 2400
A20: Consumables / linen (annual) | B20: 2400
A21: Maintenance (annual) | B21: 3500
A22: Council rates (annual) | B22: 3800
A23: Listing supplies (annual) | B23: 800
A24: Setup & financing
A25: Furnishing & setup (one-off) | B25: 30000
A26: Amortisation period (years) | B26: 5
A27: Has mortgage? (1=yes, 0=no) | B27: 0
A28: Loan balance | B28: 0
A29: Interest rate | B29: 0.062
A30: Long-term rental baseline
A31: Weekly rent | B31: 750 | C31: USER-PROVIDED
A32: Vacancy (weeks/year) | B32: 2
A33: Management fee (%) | B33: 0.07
A34: Maintenance (annual) | B34: 1500
A35: Council rates (annual) | B35: 3800
A36: Insurance (annual) | B36: 1000

Sheet Scenarios
A1: STR Scenarios vs Long-Term Rental (AUD/yr)
A3: Line | B3: Conservative | C3: Base | D3: Aggressive
A4: Occupancy | C4: =Inputs!B9 | D4: =Inputs!C9 | E4: =Inputs!D9
A5: ADR | C5: =Inputs!B10 | D5: =Inputs!C10 | E5: =Inputs!D10
A6: Nights booked | C6: =Inputs!B9*365 | D6: =Inputs!C9*365 | E6: =Inputs!D9*365
A7: Gross revenue | C7: =Inputs!B11 | D7: =Inputs!C11 | E7: =Inputs!D11
A8: less ACT levy | C8: =-C7*Inputs!B13 | D8: =-D7*Inputs!B13 | E8: =-E7*Inputs!B13
A9: less platform fee | C9: =-C7*Inputs!B17 | D9: =-D7*Inputs!B17 | E9: =-E7*Inputs!B17
A10: less management fee | C10: =-C7*Inputs!B16 | D10: =-D7*Inputs!B16 | E10: =-E7*Inputs!B16
A11: less fixed opex | C11: =-(Inputs!B18+Inputs!B19+Inputs!B20+Inputs!B21+Inputs!B22+Inputs!B23) | D11: =-(Inputs!B18+Inputs!B19+Inputs!B20+Inputs!B21+Inputs!B22+Inputs!B23) | E11: =-(Inputs!B18+Inputs!B19+Inputs!B20+Inputs!B21+Inputs!B22+Inputs!B23)
A12: Net operating income (NOI) | C12: =C7+SUM(C8:C11) | D12: =D7+SUM(D8:D11) | E12: =E7+SUM(E8:E11)
A13: less furnishing amortisation | C13: =-Inputs!B25/Inputs!B26 | D13: =-Inputs!B25/Inputs!B26 | E13: =-Inputs!B25/Inputs!B26
A14: less mortgage interest | C14: =-Inputs!B27*Inputs!B28*Inputs!B29 | D14: =-Inputs!B27*Inputs!B28*Inputs!B29 | E14: =-Inputs!B27*Inputs!B28*Inputs!B29
A15: Net cash flow | C15: =C12+C13+C14 | D15: =D12+D13+D14 | E15: =E12+E13+E14
A17: Gross yield (rev / value) | C17: =C7/Inputs!B5 | D17: =D7/Inputs!B5 | E17: =E7/Inputs!B5
A18: Net yield (NOI / value) | C18: =C12/Inputs!B5 | D18: =D12/Inputs!B5 | E18: =E12/Inputs!B5
A20: Long-term rental baseline
A21: LTR gross income | B21: =Inputs!B31*(52-Inputs!B32)
A22: LTR NOI | B22: =B21-B21*Inputs!B33-Inputs!B34-Inputs!B35-Inputs!B36
A23: LTR net yield | B23: =B22/Inputs!B5
A25: STR NOI − LTR NOI | C25: =C12-$B$22 | D25: =D12-$B$22 | E25: =E12-$B$22
A26: Break-even gross rev to match LTR | B26: =(B22+(Inputs!B18+Inputs!B19+Inputs!B20+Inputs!B21+Inputs!B22+Inputs!B23))/(1-Inputs!B13-Inputs!B17-Inputs!B16)
A27: → implied occupancy at Base ADR | B27: =B26/(Inputs!C10*365)

Sheet Sensitivity
A1: Sensitivity — STR Net Yield by Occupancy × ADR
A2: NOI ÷ property value, current levy & costs. Compare to LTR net yield (below).
A4: ADR ↓ / Occ → | B4: 0.3 | C4: 0.4 | D4: 0.5 | E4: 0.6 | F4: 0.7 | G4: 0.8
A5: 250 | B5: =($A5*B$4*365*(1-Inputs!B13-Inputs!B17-Inputs!B16)-(Inputs!B18+Inputs!B19+Inputs!B20+Inputs!B21+Inputs!B22+Inputs!B23))/Inputs!B5 | C5: =($A5*C$4*365*(1-Inputs!B13-Inputs!B17-Inputs!B16)-(Inputs!B18+Inputs!B19+Inputs!B20+Inputs!B21+Inputs!B22+Inputs!B23))/Inputs!B5 | D5: =($A5*D$4*365*(1-Inputs!B13-Inputs!B17-Inputs!B16)-(Inputs!B18+Inputs!B19+Inputs!B20+Inputs!B21+Inputs!B22+Inputs!B23))/Inputs!B5 | E5: =($A5*E$4*365*(1-Inputs!B13-Inputs!B17-Inputs!B16)-(Inputs!B18+Inputs!B19+Inputs!B20+Inputs!B21+Inputs!B22+Inputs!B23))/Inputs!B5 | F5: =($A5*F$4*365*(1-Inputs!B13-Inputs!B17-Inputs!B16)-(Inputs!B18+Inputs!B19+Inputs!B20+Inputs!B21+Inputs!B22+Inputs!B23))/Inputs!B5 | G5: =($A5*G$4*365*(1-Inputs!B13-Inputs!B17-Inputs!B16)-(Inputs!B18+Inputs!B19+Inputs!B20+Inputs!B21+Inputs!B22+Inputs!B23))/Inputs!B5
A6: 300 | B6: =($A6*B$4*365*(1-Inputs!B13-Inputs!B17-Inputs!B16)-(Inputs!B18+Inputs!B19+Inputs!B20+Inputs!B21+Inputs!B22+Inputs!B23))/Inputs!B5 | C6: =($A6*C$4*365*(1-Inputs!B13-Inputs!B17-Inputs!B16)-(Inputs!B18+Inputs!B19+Inputs!B20+Inputs!B21+Inputs!B22+Inputs!B23))/Inputs!B5 | D6: =($A6*D$4*365*(1-Inputs!B13-Inputs!B17-Inputs!B16)-(Inputs!B18+Inputs!B19+Inputs!B20+Inputs!B21+Inputs!B22+Inputs!B23))/Inputs!B5 | E6: =($A6*E$4*365*(1-Inputs!B13-Inputs!B17-Inputs!B16)-(Inputs!B18+Inputs!B19+Inputs!B20+Inputs!B21+Inputs!B22+Inputs!B23))/Inputs!B5 | F6: =($A6*F$4*365*(1-Inputs!B13-Inputs!B17-Inputs!B16)-(Inputs!B18+Inputs!B19+Inputs!B20+Inputs!B21+Inputs!B22+Inputs!B23))/Inputs!B5 | G6: =($A6*G$4*365*(1-Inputs!B13-Inputs!B17-Inputs!B16)-(Inputs!B18+Inputs!B19+Inputs!B20+Inputs!B21+Inputs!B22+Inputs!B23))/Inputs!B5
A7: 350 | B7: =($A7*B$4*365*(1-Inputs!B13-Inputs!B17-Inputs!B16)-(Inputs!B18+Inputs!B19+Inputs!B20+Inputs!B21+Inputs!B22+Inputs!B23))/Inputs!B5 | C7: =($A7*C$4*365*(1-Inputs!B13-Inputs!B17-Inputs!B16)-(Inputs!B18+Inputs!B19+Inputs!B20+Inputs!B21+Inputs!B22+Inputs!B23))/Inputs!B5 | D7: =($A7*D$4*365*(1-Inputs!B13-Inputs!B17-Inputs!B16)-(Inputs!B18+Inputs!B19+Inputs!B20+Inputs!B21+Inputs!B22+Inputs!B23))/Inputs!B5 | E7: =($A7*E$4*365*(1-Inputs!B13-Inputs!B17-Inputs!B16)-(Inputs!B18+Inputs!B19+Inputs!B20+Inputs!B21+Inputs!B22+Inputs!B23))/Inputs!B5 | F7: =($A7*F$4*365*(1-Inputs!B13-Inputs!B17-Inputs!B16)-(Inputs!B18+Inputs!B19+Inputs!B20+Inputs!B21+Inputs!B22+Inputs!B23))/Inputs!B5 | G7: =($A7*G$4*365*(1-Inputs!B13-Inputs!B17-Inputs!B16)-(Inputs!B18+Inputs!B19+Inputs!B20+Inputs!B21+Inputs!B22+Inputs!B23))/Inputs!B5
A8: 400 | B8: =($A8*B$4*365*(1-Inputs!B13-Inputs!B17-Inputs!B16)-(Inputs!B18+Inputs!B19+Inputs!B20+Inputs!B21+Inputs!B22+Inputs!B23))/Inputs!B5 | C8: =($A8*C$4*365*(1-Inputs!B13-Inputs!B17-Inputs!B16)-(Inputs!B18+Inputs!B19+Inputs!B20+Inputs!B21+Inputs!B22+Inputs!B23))/Inputs!B5 | D8: =($A8*D$4*365*(1-Inputs!B13-Inputs!B17-Inputs!B16)-(Inputs!B18+Inputs!B19+Inputs!B20+Inputs!B21+Inputs!B22+Inputs!B23))/Inputs!B5 | E8: =($A8*E$4*365*(1-Inputs!B13-Inputs!B17-Inputs!B16)-(Inputs!B18+Inputs!B19+Inputs!B20+Inputs!B21+Inputs!B22+Inputs!B23))/Inputs!B5 | F8: =($A8*F$4*365*(1-Inputs!B13-Inputs!B17-Inputs!B16)-(Inputs!B18+Inputs!B19+Inputs!B20+Inputs!B21+Inputs!B22+Inputs!B23))/Inputs!B5 | G8: =($A8*G$4*365*(1-Inputs!B13-Inputs!B17-Inputs!B16)-(Inputs!B18+Inputs!B19+Inputs!B20+Inputs!B21+Inputs!B22+Inputs!B23))/Inputs!B5
A9: 450 | B9: =($A9*B$4*365*(1-Inputs!B13-Inputs!B17-Inputs!B16)-(Inputs!B18+Inputs!B19+Inputs!B20+Inputs!B21+Inputs!B22+Inputs!B23))/Inputs!B5 | C9: =($A9*C$4*365*(1-Inputs!B13-Inputs!B17-Inputs!B16)-(Inputs!B18+Inputs!B19+Inputs!B20+Inputs!B21+Inputs!B22+Inputs!B23))/Inputs!B5 | D9: =($A9*D$4*365*(1-Inputs!B13-Inputs!B17-Inputs!B16)-(Inputs!B18+Inputs!B19+Inputs!B20+Inputs!B21+Inputs!B22+Inputs!B23))/Inputs!B5 | E9: =($A9*E$4*365*(1-Inputs!B13-Inputs!B17-Inputs!B16)-(Inputs!B18+Inputs!B19+Inputs!B20+Inputs!B21+Inputs!B22+Inputs!B23))/Inputs!B5 | F9: =($A9*F$4*365*(1-Inputs!B13-Inputs!B17-Inputs!B16)-(Inputs!B18+Inputs!B19+Inputs!B20+Inputs!B21+Inputs!B22+Inputs!B23))/Inputs!B5 | G9: =($A9*G$4*365*(1-Inputs!B13-Inputs!B17-Inputs!B16)-(Inputs!B18+Inputs!B19+Inputs!B20+Inputs!B21+Inputs!B22+Inputs!B23))/Inputs!B5
A10: 500 | B10: =($A10*B$4*365*(1-Inputs!B13-Inputs!B17-Inputs!B16)-(Inputs!B18+Inputs!B19+Inputs!B20+Inputs!B21+Inputs!B22+Inputs!B23))/Inputs!B5 | C10: =($A10*C$4*365*(1-Inputs!B13-Inputs!B17-Inputs!B16)-(Inputs!B18+Inputs!B19+Inputs!B20+Inputs!B21+Inputs!B22+Inputs!B23))/Inputs!B5 | D10: =($A10*D$4*365*(1-Inputs!B13-Inputs!B17-Inputs!B16)-(Inputs!B18+Inputs!B19+Inputs!B20+Inputs!B21+Inputs!B22+Inputs!B23))/Inputs!B5 | E10: =($A10*E$4*365*(1-Inputs!B13-Inputs!B17-Inputs!B16)-(Inputs!B18+Inputs!B19+Inputs!B20+Inputs!B21+Inputs!B22+Inputs!B23))/Inputs!B5 | F10: =($A10*F$4*365*(1-Inputs!B13-Inputs!B17-Inputs!B16)-(Inputs!B18+Inputs!B19+Inputs!B20+Inputs!B21+Inputs!B22+Inputs!B23))/Inputs!B5 | G10: =($A10*G$4*365*(1-Inputs!B13-Inputs!B17-Inputs!B16)-(Inputs!B18+Inputs!B19+Inputs!B20+Inputs!B21+Inputs!B22+Inputs!B23))/Inputs!B5
A12: LTR net yield: | B12: =Scenarios!B22/Inputs!B5
